wazimap_mapit/__init__.py
wazimap_mapit/geo.py
wazimap_mapit/static/js/maps_mapit.js
wazimap_mapit/static/js/profile_map_mapit.js
wazimap_mapit/templates/settings_js.html
wazimap_mapit-0.5.4.dist-info/DESCRIPTION.rst
wazimap_mapit-0.5.4.dist-info/METADATA
wazimap_mapit-0.5.4.dist-info/metadata.json
wazimap_mapit-0.5.4.dist-info/RECORD
wazimap_mapit-0.5.4.dist-info/top_level.txt
wazimap_mapit-0.5.4.dist-info/WHEEL
